tfsumpy/__init__.py
tfsumpy/__main__.py
tfsumpy/analyzer.py
tfsumpy/context.py
tfsumpy/plan/analyzer.py
tfsumpy/plan/reporter.py
tfsumpy/plugins.py
tfsumpy/reporter.py
tfsumpy/reporters/base_reporter.py
tfsumpy/resource.py
tfsumpy/rules_config.json
tfsumpy/templates/plan_report.md
tfsumpy-0.2.1.dist-info/LICENSE
tfsumpy-0.2.1.dist-info/METADATA
tfsumpy-0.2.1.dist-info/WHEEL
tfsumpy-0.2.1.dist-info/entry_points.txt
tfsumpy-0.2.1.dist-info/RECORD
