Metadata-Version: 2.3
Name: tfsumpy
Version: 0.2.1
Summary: A Python tool for Terraform state summary
License: MIT
Keywords: terraform,infrastructure,cloud,DevOps
Author: Rafael H de Carvalho
Author-email: rafaelherik@gmail.com
Requires-Python: >=3.10,<4.0
Classifier: Development Status :: 3 - Alpha
Classifier: Intended Audience :: Developers
Classifier: License :: OSI Approved :: MIT License
Classifier: Programming Language :: Python :: 3
Classifier: Programming Language :: Python :: 3.10
Classifier: Programming Language :: Python :: 3.11
Classifier: Programming Language :: Python :: 3.12
Classifier: Programming Language :: Python :: 3.13
Classifier: Topic :: Software Development :: Build Tools
Classifier: Topic :: System :: Systems Administration
Provides-Extra: dev
Requires-Dist: colorama (>=0.4.6)
Requires-Dist: jinja2 (>=3.1.6,<4.0.0)
Requires-Dist: jsonschema (>=3.2.0)
Requires-Dist: pytest (>=7.0.0)
Requires-Dist: pyyaml (>=5.1)
Project-URL: Bug Tracker, https://github.com/rafaelherik/tfsumpy/issues
Project-URL: Documentation, https://github.com/rafaelherik/tfsumpy
Project-URL: Repository, https://github.com/rafaelherik/tfsumpy
Project-URL: Source Code, https://github.com/rafaelherik/tfsumpy
